Digo/AzureCloud.py
Digo/DigoCore.py
Digo/Error.py
Digo/ExceptionHandler.py
Digo/Network.py
Digo/Project.py
Digo/Singletone.py
Digo/SystemMetrics.py
Digo/Utils.py
Digo/__init__.py
Digo-0.1.6.dist-info/METADATA
Digo-0.1.6.dist-info/WHEEL
Digo-0.1.6.dist-info/top_level.txt
Digo-0.1.6.dist-info/RECORD
