Metadata-Version: 2.1
Name: Digo
Version: 0.1.6
Summary: UNKNOWN
Home-page: UNKNOWN
Author: DiggerWorks
Author-email: support@digger.works
License: UNKNOWN
Keywords: digo,ml
Platform: UNKNOWN
Requires-Dist: azure-core
Requires-Dist: azure-storage-blob
Requires-Dist: Pillow
Requires-Dist: numpy
Requires-Dist: requests
Requires-Dist: psutil
Requires-Dist: nvgpu
Requires-Dist: argparse
Requires-Dist: inputimeout
